flake8_ets/__init__.py
flake8_ets/copyright_header.py
flake8_ets/version.py
flake8_ets/tests/__init__.py
flake8_ets/tests/test_copyright_header.py
flake8_ets-1.0.1.dist-info/LICENSE.txt
flake8_ets-1.0.1.dist-info/METADATA
flake8_ets-1.0.1.dist-info/WHEEL
flake8_ets-1.0.1.dist-info/entry_points.txt
flake8_ets-1.0.1.dist-info/top_level.txt
flake8_ets-1.0.1.dist-info/RECORD
