Metadata-Version: 2.1
Name: flake8-ets
Version: 1.0.1
Summary: flake8 plugin for checking Enthought Tool Suite copyright headers.
Home-page: https://github.com/enthought/ets-copyright-checker
Author: Enthought
Author-email: info@enthought.com
License: BSD
Classifier: Development Status :: 3 - Alpha
Classifier: Intended Audience :: Developers
Classifier: License :: OSI Approved :: BSD License
Classifier: Operating System :: OS Independent
Classifier: Programming Language :: Python :: 3
Requires-Python: >=3.5
License-File: LICENSE.txt
Requires-Dist: flake8
